Mon Jan 23 12:23:54 2006
0	LOAD_CONST        1
3	STORE_NAME        'x'
6	LOAD_CONST        'code_object test'
9	MAKE_FUNCTION_0   ''
12	STORE_NAME        'test'
15	LOAD_CONST        ''
18	RETURN_VALUE      ''

0	LOAD_GLOBAL       'x'
3	LOAD_CONST        1
6	COMPARE_OP        '=='
9	JUMP_IF_FALSE     '21'
12	POP_TOP           ''
13	LOAD_CONST        'Jedna'
16	PRINT_ITEM        ''
17	PRINT_NEWLINE     ''
18	JUMP_FORWARD      '27'
21_0	COME_FROM         ''
21	POP_TOP           ''
22	LOAD_CONST        'Dva'
25	PRINT_ITEM        ''
26	PRINT_NEWLINE     ''
27_0	COME_FROM         ''
27	LOAD_CONST        ''
30	RETURN_VALUE      ''

x = 1

def test():
    if (x == 1):
        print 'Jedna'
    else:
        print 'Dva'



+++ okay decompyling test.pyc 5
decompyled 1 files: 1 okay, 0 failed, 0 verify failed
Mon Jan 23 12:23:54 2006
